{
  "title": "United Kingdom population mid year estimate",
  "source dataset id": "pop",
  "release date": "27-11-2025",
  "important notes": "The UK estimate for mid-2025 is provisional and rounded to the nearest 1000; all other estimates are rounded to the nearest 100",
  "description": "Mid-year population estimates relate to the usually resident population. They account for long-term international migrants (people who change their country of usual residence for a period of 12 months or more) but do not account for short-term migrants (people who come to or leave the country for a period of less than 12 months). This approach is consistent with the standard UN definition for population estimates which is based upon the concept of usual residence and includes people who reside, or intend to reside, in the country for at least twelve months, whatever their nationality.",
  "chart-type": "line-chart",
  "source": "https://www.ons.gov.uk/peoplepopulationandcommunity/populationandmigration/populationestimates/timeseries/ukpop/pop",
  "data": [
    {
      "year": "1971",
      "population mid-year estimate": "55928000"
    },
    {
      "year": "1972",
      "population mid-year estimate": "56096700"
    },
    {
      "year": "1973",
      "population mid-year estimate": "56222900"
    },
    {
      "year": "1974",
      "population mid-year estimate": "56235600"
    },
    {
      "year": "1975",
      "population mid-year estimate": "56225700"
    },
    {
      "year": "1976",
      "population mid-year estimate": "56216100"
    },
    {
      "year": "1977",
      "population mid-year estimate": "56189900"
    },
    {
      "year": "1978",
      "population mid-year estimate": "56178000"
    },
    {
      "year": "1979",
      "population mid-year estimate": "56240100"
    },
    {
      "year": "1980",
      "population mid-year estimate": "56329700"
    },
    {
      "year": "1981",
      "population mid-year estimate": "56357500"
    },
    {
      "year": "1982",
      "population mid-year estimate": "56290700"
    },
    {
      "year": "1983",
      "population mid-year estimate": "56315700"
    },
    {
      "year": "1984",
      "population mid-year estimate": "56409300"
    },
    {
      "year": "1985",
      "population mid-year estimate": "56554000"
    },
    {
      "year": "1986",
      "population mid-year estimate": "56683800"
    },
    {
      "year": "1987",
      "population mid-year estimate": "56804000"
    },
    {
      "year": "1988",
      "population mid-year estimate": "56916400"
    },
    {
      "year": "1989",
      "population mid-year estimate": "57076500"
    },
    {
      "year": "1990",
      "population mid-year estimate": "57237500"
    },
    {
      "year": "1991",
      "population mid-year estimate": "57438700"
    },
    {
      "year": "1992",
      "population mid-year estimate": "57584500"
    },
    {
      "year": "1993",
      "population mid-year estimate": "57713900"
    },
    {
      "year": "1994",
      "population mid-year estimate": "57862100"
    },
    {
      "year": "1995",
      "population mid-year estimate": "58024800"
    },
    {
      "year": "1996",
      "population mid-year estimate": "58164400"
    },
    {
      "year": "1997",
      "population mid-year estimate": "58314200"
    },
    {
      "year": "1998",
      "population mid-year estimate": "58474900"
    },
    {
      "year": "1999",
      "population mid-year estimate": "58684400"
    },
    {
      "year": "2000",
      "population mid-year estimate": "58886100"
    },
    {
      "year": "2001",
      "population mid-year estimate": "59113000"
    },
    {
      "year": "2002",
      "population mid-year estimate": "59365700"
    },
    {
      "year": "2003",
      "population mid-year estimate": "59636700"
    },
    {
      "year": "2004",
      "population mid-year estimate": "59950400"
    },
    {
      "year": "2005",
      "population mid-year estimate": "60413300"
    },
    {
      "year": "2006",
      "population mid-year estimate": "60827000"
    },
    {
      "year": "2007",
      "population mid-year estimate": "61319100"
    },
    {
      "year": "2008",
      "population mid-year estimate": "61823800"
    },
    {
      "year": "2009",
      "population mid-year estimate": "62260500"
    },
    {
      "year": "2010",
      "population mid-year estimate": "62759500"
    },
    {
      "year": "2011",
      "population mid-year estimate": "63285100"
    },
    {
      "year": "2012",
      "population mid-year estimate": "63710500"
    },
    {
      "year": "2013",
      "population mid-year estimate": "64138200"
    },
    {
      "year": "2014",
      "population mid-year estimate": "64618700"
    },
    {
      "year": "2015",
      "population mid-year estimate": "65087000"
    },
    {
      "year": "2016",
      "population mid-year estimate": "65605800"
    },
    {
      "year": "2017",
      "population mid-year estimate": "65964300"
    },
    {
      "year": "2018",
      "population mid-year estimate": "66286700"
    },
    {
      "year": "2019",
      "population mid-year estimate": "66627500"
    },
    {
      "year": "2020",
      "population mid-year estimate": "66739900"
    },
    {
      "year": "2021",
      "population mid-year estimate": "66978000"
    },
    {
      "year": "2022",
      "population mid-year estimate": "67636100"
    },
    {
      "year": "2023",
      "population mid-year estimate": "68526200"
    },
    {
      "year": "2024",
      "population mid-year estimate": "69281400"
    },
    {
      "year": "2025",
      "population mid-year estimate": "69487000"
    }
  ]
}
